{
  "token": "insert your discord bot's token here",
  "clientID": "insert your discord app's client ID here",
  "prefix": "fulp",
  "ownerID": "",
  "NGappID": "",
  "NGencKey": "",
  "GOOGLE_API_KEY": "uhhh idk lol",
  "MMappID": "",
  // FULP TRON GOOGLE DRIVE SHIT GOES HERE
  "type": "service_account",
  "project_id": "fulptron",
  "private_key_id": "",
  "private_key": "",
  "client_email": "fulptrongdrive@fulptron.iam.gserviceaccount.com",
  "client_id": "117511602438526067220",
  "auth_uri": "https://accounts.google.com/o/oauth2/auth",
  "token_uri": "https://oauth2.googleapis.com/token",
  "auth_provider_x509_cert_url": "https://www.googleapis.com/oauth2/v1/certs",
  "client_x509_cert_url": "https://www.googleapis.com/robot/v1/metadata/x509/fulptrongdrive%40fulptron.iam.gserviceaccount.com"
}
